tutcatalog5/__init__.py
tutcatalog5-0.1.0.dist-info/METADATA
tutcatalog5-0.1.0.dist-info/WHEEL
tutcatalog5-0.1.0.dist-info/licenses/LICENSE.md
tutcatalog5-0.1.0.dist-info/RECORD
